{
"type": "FeatureCollection",
"name": "waypoints",
"crs": { "type": "name", "properties": { "name": "urn:ogc:def:crs:OGC:1.3:CRS84" } },
"features": [
{ "type": "Feature", "properties": { "name": "continue" }, "geometry": { "type": "Point", "coordinates": [ 7.144793, 51.266614 ] } },
{ "type": "Feature", "properties": { "name": "arrive at destination" }, "geometry": { "type": "Point", "coordinates": [ 7.14643, 51.274213 ] } }
]
}
