{
"type": "FeatureCollection",
"name": "waypoints",
"crs": { "type": "name", "properties": { "name": "urn:ogc:def:crs:OGC:1.3:CRS84" } },
"features": [
{ "type": "Feature", "properties": { "name": "continue" }, "geometry": { "type": "Point", "coordinates": [ 6.697356, 51.207473 ] } },
{ "type": "Feature", "properties": { "name": "arrive at destination" }, "geometry": { "type": "Point", "coordinates": [ 6.812762, 51.219667 ] } }
]
}
